odoo/addons/account_bank_statement_import_mt940_pl_raiffeisen/README.rst
odoo/addons/account_bank_statement_import_mt940_pl_raiffeisen/__init__.py
odoo/addons/account_bank_statement_import_mt940_pl_raiffeisen/__manifest__.py
odoo/addons/account_bank_statement_import_mt940_pl_raiffeisen/account_bank_statement_import.py
odoo/addons/account_bank_statement_import_mt940_pl_raiffeisen/mt940.py
odoo/addons/account_bank_statement_import_mt940_pl_raiffeisen/i18n/account_bank_statement_import_mt940_pl_raiffeisen.pot
odoo/addons/account_bank_statement_import_mt940_pl_raiffeisen/readme/CONTRIBUTORS.rst
odoo/addons/account_bank_statement_import_mt940_pl_raiffeisen/readme/CREDITS.rst
odoo/addons/account_bank_statement_import_mt940_pl_raiffeisen/readme/DESCRIPTION.rst
odoo/addons/account_bank_statement_import_mt940_pl_raiffeisen/static/description/icon.png
odoo/addons/account_bank_statement_import_mt940_pl_raiffeisen/static/description/index.html
odoo11_addon_account_bank_statement_import_mt940_pl_raiffeisen-11.0.1.0.0.99.dev6.dist-info/METADATA
odoo11_addon_account_bank_statement_import_mt940_pl_raiffeisen-11.0.1.0.0.99.dev6.dist-info/WHEEL
odoo11_addon_account_bank_statement_import_mt940_pl_raiffeisen-11.0.1.0.0.99.dev6.dist-info/top_level.txt
odoo11_addon_account_bank_statement_import_mt940_pl_raiffeisen-11.0.1.0.0.99.dev6.dist-info/RECORD
